stonesoup/__init__.py
stonesoup/base.py
stonesoup/buffered_generator.py
stonesoup/config.py
stonesoup/kernel.py
stonesoup/plotter.py
stonesoup/plugins.py
stonesoup/serialise.py
stonesoup/stitcher.py
stonesoup/dataassociator/__init__.py
stonesoup/dataassociator/_assignment.py
stonesoup/dataassociator/_ehm.py
stonesoup/dataassociator/base.py
stonesoup/dataassociator/clearmot.py
stonesoup/dataassociator/general.py
stonesoup/dataassociator/neighbour.py
stonesoup/dataassociator/probability.py
stonesoup/dataassociator/tracktotrack.py
stonesoup/dataassociator/tree.py
stonesoup/dataassociator/mfa/__init__.py
stonesoup/dataassociator/mfa/_init.py
stonesoup/dataassociator/mfa/_step.py
stonesoup/deleter/__init__.py
stonesoup/deleter/base.py
stonesoup/deleter/error.py
stonesoup/deleter/multi.py
stonesoup/deleter/time.py
stonesoup/detector/__init__.py
stonesoup/detector/_video.py
stonesoup/detector/base.py
stonesoup/detector/tensorflow.py
stonesoup/detector/tensornets.py
stonesoup/feeder/__init__.py
stonesoup/feeder/base.py
stonesoup/feeder/filter.py
stonesoup/feeder/geo.py
stonesoup/feeder/image.py
stonesoup/feeder/multi.py
stonesoup/feeder/time.py
stonesoup/feeder/track.py
stonesoup/functions/__init__.py
stonesoup/functions/graph.py
stonesoup/functions/interpolate.py
stonesoup/functions/orbital.py
stonesoup/gater/__init__.py
stonesoup/gater/base.py
stonesoup/gater/distance.py
stonesoup/gater/filtered.py
stonesoup/hypothesiser/__init__.py
stonesoup/hypothesiser/base.py
stonesoup/hypothesiser/categorical.py
stonesoup/hypothesiser/composite.py
stonesoup/hypothesiser/distance.py
stonesoup/hypothesiser/gaussianmixture.py
stonesoup/hypothesiser/mfa.py
stonesoup/hypothesiser/probability.py
stonesoup/hypothesiser/simple.py
stonesoup/initiator/__init__.py
stonesoup/initiator/base.py
stonesoup/initiator/categorical.py
stonesoup/initiator/composite.py
stonesoup/initiator/particle.py
stonesoup/initiator/simple.py
stonesoup/initiator/wrapper.py
stonesoup/measures/__init__.py
stonesoup-1.8.dist-info/licenses/LICENSE
stonesoup-1.8.dist-info/METADATA
stonesoup-1.8.dist-info/WHEEL
stonesoup-1.8.dist-info/top_level.txt
stonesoup-1.8.dist-info/RECORD
