Metadata-Version: 2.4
Name: stonesoup
Version: 1.8
Summary: A tracking and state estimation framework
Maintainer-email: Defence Science and Technology Laboratory UK <stonesoup@dstl.gov.uk>
License-Expression: MIT
Project-URL: Homepage, https://github.com/dstl/Stone-Soup
Project-URL: Documentation, https://stonesoup.readthedocs.org
Project-URL: Release Notes, https://github.com/dstl/Stone-Soup/releases
Project-URL: Issues, https://github.com/dstl/Stone-Soup/issues
Classifier: Development Status :: 5 - Production/Stable
Classifier: Intended Audience :: Science/Research
Classifier: Operating System :: OS Independent
Classifier: Programming Language :: Python :: 3 :: Only
Classifier: Topic :: Scientific/Engineering
Requires-Python: >=3.10
License-File: LICENSE
Requires-Dist: matplotlib
Requires-Dist: numpy>=1.17
Requires-Dist: ordered-set
Requires-Dist: plotly>=5.0
Requires-Dist: pymap3d
Requires-Dist: rtree
Requires-Dist: ruamel.yaml>=0.16.5
Requires-Dist: scipy
Requires-Dist: utm
Provides-Extra: dev
Requires-Dist: confluent-kafka; extra == "dev"
Requires-Dist: coverage>=7.2; extra == "dev"
Requires-Dist: flake8; extra == "dev"
Requires-Dist: folium; extra == "dev"
Requires-Dist: h5py; extra == "dev"
Requires-Dist: ortools; extra == "dev"
Requires-Dist: pandas; extra == "dev"
Requires-Dist: pillow; extra == "dev"
Requires-Dist: pytest-cov; extra == "dev"
Requires-Dist: pytest-remotedata; extra == "dev"
Requires-Dist: pytest-skip-slow; extra == "dev"
Requires-Dist: Sphinx; extra == "dev"
Requires-Dist: sphinx-gallery>=0.17; extra == "dev"
Requires-Dist: sphinx_rtd_theme>=1.2; extra == "dev"
Provides-Extra: video
Requires-Dist: ffmpeg-python; extra == "video"
Requires-Dist: moviepy; extra == "video"
Requires-Dist: opencv-python; extra == "video"
Provides-Extra: tensorflow
Requires-Dist: tensorflow>=2.2.0; extra == "tensorflow"
Provides-Extra: tensornets
Requires-Dist: tensorflow>=2.2.0; extra == "tensornets"
Requires-Dist: tensornets; extra == "tensornets"
Provides-Extra: orbital
Requires-Dist: astropy; extra == "orbital"
Provides-Extra: mfa
Requires-Dist: ortools; extra == "mfa"
Provides-Extra: ehm
Requires-Dist: pyehm; extra == "ehm"
Provides-Extra: optuna
Requires-Dist: optuna; extra == "optuna"
Provides-Extra: ode
Requires-Dist: torch; extra == "ode"
Provides-Extra: roadnet
Requires-Dist: geopandas; extra == "roadnet"
Requires-Dist: networkx; extra == "roadnet"
Dynamic: license-file
